{
  "id": 2,
  "acc_path": "val",
  "Kernel read": "https://gitlab.flux.utah.edu/xcap/xcap-capability-linux/-/blob/llvm_v4.8/drivers/hwmon/hwmon-vid.c#L69 | vid_from_reg",
  "Drv update": ""
}
{
  "id": 3,
  "acc_path": "vrm",
  "Kernel read": "https://gitlab.flux.utah.edu/xcap/xcap-capability-linux/-/blob/llvm_v4.8/drivers/hwmon/hwmon-vid.c#L69 | vid_from_reg",
  "Drv update": ""
}
{
  "id": 5,
  "acc_path": "value",
  "Kernel read": "https://gitlab.flux.utah.edu/xcap/xcap-capability-linux/-/blob/llvm_v4.8/drivers/i2c/i2c-core-smbus.c#L158 | i2c_smbus_write_byte_data",
  "Drv update": ""
}
{
  "id": 6,
  "acc_path": "nval",
  "Kernel read": "https://gitlab.flux.utah.edu/xcap/xcap-capability-linux/-/blob/llvm_v4.8/drivers/base/property.c#L142 | device_property_read_u32_array",
  "Drv update": ""
}
{
  "id": 7,
  "acc_path": "int",
  "Kernel read": "https://gitlab.flux.utah.edu/xcap/xcap-capability-linux/-/blob/llvm_v4.8/drivers/hwmon/adt7475.c#L1631 | adt7475_probe",
  "Drv update": ""
}
{
  "id": 8,
  "acc_path": "int",
  "Kernel read": "https://gitlab.flux.utah.edu/xcap/xcap-capability-linux/-/blob/llvm_v4.8/drivers/hwmon/adt7475.c#L1313 | adt7475_detect",
  "Drv update": ""
}
{
  "id": 9,
  "acc_path": "ssize_t",
  "Kernel read": "https://gitlab.flux.utah.edu/xcap/xcap-capability-linux/-/blob/llvm_v4.8/drivers/hwmon/adt7475.c#L1051 | vrm_show",
  "Drv update": ""
}
{
  "id": 10,
  "acc_path": "ssize_t",
  "Kernel read": "https://gitlab.flux.utah.edu/xcap/xcap-capability-linux/-/blob/llvm_v4.8/drivers/hwmon/adt7475.c#L1058 | vrm_store",
  "Drv update": ""
}
{
  "id": 11,
  "acc_path": "ssize_t",
  "Kernel read": "https://gitlab.flux.utah.edu/xcap/xcap-capability-linux/-/blob/llvm_v4.8/drivers/hwmon/adt7475.c#L1051 | vrm_show",
  "Drv update": ""
}
{
  "id": 12,
  "acc_path": "ssize_t",
  "Kernel read": "https://gitlab.flux.utah.edu/xcap/xcap-capability-linux/-/blob/llvm_v4.8/drivers/hwmon/adt7475.c#L1051 | vrm_show",
  "Drv update": ""
}
{
  "id": 13,
  "acc_path": "ssize_t",
  "Kernel read": "https://gitlab.flux.utah.edu/xcap/xcap-capability-linux/-/blob/llvm_v4.8/drivers/hwmon/adt7475.c#L1058 | vrm_store",
  "Drv update": ""
}
